<annotation>
	<folder>images</folder>
	<filename>withhoutt_massk4.jpeg</filename>
	<path>C:\Users\MSI\Documents\Face-Mask-Detection-\dataset\images\withhoutt_massk4.jpeg</path>
	<source>
		<database>Unknown</database>
	</source>
	<size>
		<width>1280</width>
		<height>960</height>
		<depth>3</depth>
	</size>
	<segmented>0</segmented>
	<object>
		<name>without_mask</name>
		<pose>Unspecified</pose>
		<truncated>0</truncated>
		<difficult>0</difficult>
		<bndbox>
			<xmin>514</xmin>
			<ymin>358</ymin>
			<xmax>617</xmax>
			<ymax>449</ymax>
		</bndbox>
	</object>
	<object>
		<name>mask_weared_incorrect</name>
		<pose>Unspecified</pose>
		<truncated>0</truncated>
		<difficult>0</difficult>
		<bndbox>
			<xmin>188</xmin>
			<ymin>296</ymin>
			<xmax>306</xmax>
			<ymax>422</ymax>
		</bndbox>
	</object>
	<object>
		<name>mask_weared_incorrect</name>
		<pose>Unspecified</pose>
		<truncated>0</truncated>
		<difficult>0</difficult>
		<bndbox>
			<xmin>887</xmin>
			<ymin>326</ymin>
			<xmax>1029</xmax>
			<ymax>456</ymax>
		</bndbox>
	</object>
</annotation>
